pybiouml/__init__.py
pybiouml/pybiouml.py
pybiouml-1.2.2.dist-info/LICENSE
pybiouml-1.2.2.dist-info/METADATA
pybiouml-1.2.2.dist-info/WHEEL
pybiouml-1.2.2.dist-info/top_level.txt
pybiouml-1.2.2.dist-info/RECORD
