Metadata-Version: 2.2
Name: pybiouml
Version: 1.2.2
Summary: Python package for using BioUML
Home-page: https://www.biouml.org/
Author: Mikhail Kulyashov & Semyon Kolmykov, Biosoft.ru
Author-email: m.kulyashov@dote.ru
Project-URL: Bug Tracker, https://github.com/Biosoft-ru/pybiouml/issues
Project-URL: Source Code, https://github.com/Biosoft-ru/pybiouml
Project-URL: Documentation, https://pybiouml.readthedocs.io/en/latest/
Classifier: Programming Language :: Python :: 3
Classifier: Programming Language :: Python :: 3 :: Only
Classifier: Programming Language :: Python :: 3.8
Classifier: Programming Language :: Python :: 3.9
Classifier: Programming Language :: Python :: 3.9
Classifier: License :: OSI Approved :: MIT License
Classifier: Operating System :: OS Independent
Classifier: Topic :: Scientific/Engineering
Requires-Python: >=3.8
License-File: LICENSE
Requires-Dist: pandas
Requires-Dist: progress
Requires-Dist: requests
Requires-Dist: requests_toolbelt
